main.py
task_3_muraway-1.0.0.dist-info/METADATA
task_3_muraway-1.0.0.dist-info/WHEEL
task_3_muraway-1.0.0.dist-info/top_level.txt
task_3_muraway-1.0.0.dist-info/RECORD
