Metadata-Version: 2.1
Name: task_3_muraway
Version: 1.0.0
Summary: task_3
Author-email: Victor <logday2017@gmail.com>
Requires-Python: >=3.6
Requires-Dist: pandas
